underworlds/__init__.py
underworlds/errors.py
underworlds/server.py
underworlds/server_pb.py
underworlds/services.py
underworlds/situations.py
underworlds/types.py
underworlds/underworlds_pb2.py
underworlds/helpers/__init__.py
underworlds/helpers/daemon.py
underworlds/helpers/geometry.py
underworlds/helpers/profile.py
underworlds/helpers/transformations.py
underworlds/tools/3d_primitives.py
underworlds/tools/__init__.py
underworlds/tools/loader.py
underworlds/tools/primitives_3d.py
underworlds/tools/visibility.py
underworlds-0.2.1.data/data/share/doc/underworlds/LICENSE
underworlds-0.2.1.data/data/share/doc/underworlds/README.md
underworlds-0.2.1.data/scripts/dna.txt
underworlds-0.2.1.data/scripts/underworlded
underworlds-0.2.1.data/scripts/uwds
underworlds-0.2.1.data/scripts/uwds-edit
underworlds-0.2.1.data/scripts/uwds-explorer
underworlds-0.2.1.data/scripts/uwds-filter
underworlds-0.2.1.data/scripts/uwds-filterc
underworlds-0.2.1.data/scripts/uwds-list
underworlds-0.2.1.data/scripts/uwds-load
underworlds-0.2.1.data/scripts/uwds-ls
underworlds-0.2.1.data/scripts/uwds-set-mesh
underworlds-0.2.1.data/scripts/uwds-show
underworlds-0.2.1.data/scripts/uwds-tf
underworlds-0.2.1.data/scripts/uwds-view
underworlds-0.2.1.data/scripts/uwds-view.orig
underworlds-0.2.1.data/scripts/uwds-visibility
underworlds-0.2.1.dist-info/DESCRIPTION.rst
underworlds-0.2.1.dist-info/METADATA
underworlds-0.2.1.dist-info/RECORD
underworlds-0.2.1.dist-info/WHEEL
underworlds-0.2.1.dist-info/metadata.json
underworlds-0.2.1.dist-info/top_level.txt
