Metadata-Version: 2.0
Name: underworlds
Version: 0.2.1
Summary: A framework for geometric and temporal representation of robotic worlds
Home-page: https://github.com/severin-lemaignan/underworlds
Author: Séverin Lemaignan
Author-email: severin.lemaignan@plymouth.ac.uk
License: ISC
Platform: UNKNOWN
Requires-Dist: pyassimp
Requires-Dist: grpcio
Requires-Dist: numpy
Requires-Dist: argcomplete
